emailer/__init__.py
emailer/contacts.py
emailer/drafter.py
emailer/message.py
emailer/sender.py
emailer/utils.py
futuremail/__init__.py
futuremail/contacts.py
futuremail/drafter.py
futuremail/message.py
futuremail/sender.py
futuremail/utils.py
futuremail-1.1.3.dist-info/LICENSE
futuremail-1.1.3.dist-info/METADATA
futuremail-1.1.3.dist-info/WHEEL
futuremail-1.1.3.dist-info/top_level.txt
futuremail-1.1.3.dist-info/RECORD
