Metadata-Version: 2.1
Name: futuremail
Version: 1.1.3
Summary: Send emails with Python
Home-page: https://github.com/wheelercj/futuremail
Author: Chris Wheeler
Author-email: christopher.wheeler.320@my.csun.edu
License: MIT
Keywords: email,smtp,futuremail
Platform: unix
Platform: linux
Platform: osx
Platform: cygwin
Platform: win32
Classifier: Programming Language :: Python :: 3 :: Only
Classifier: Programming Language :: Python :: 3
Classifier: Programming Language :: Python :: 3.8
Classifier: Programming Language :: Python :: 3.9
Classifier: Programming Language :: Python :: 3.10
Classifier: Programming Language :: Python :: 3.11
Requires-Python: >=3.8
License-File: LICENSE
Requires-Dist: mistune
Requires-Dist: openpyxl
